alertiqo/__init__.py
alertiqo/client.py
alertiqo/middleware.py
alertiqo-1.0.3.dist-info/licenses/LICENSE
alertiqo-1.0.3.dist-info/METADATA
alertiqo-1.0.3.dist-info/WHEEL
alertiqo-1.0.3.dist-info/top_level.txt
alertiqo-1.0.3.dist-info/RECORD
