Metadata-Version: 2.4
Name: alertiqo
Version: 1.0.3
Summary: Alertiqo SDK for Python error tracking
Author-email: Muhammad Hamizi Jaminan <hello@hamizi.net>
License: MIT
Project-URL: Homepage, https://github.com/hymns/alertiqo-client-python
Project-URL: Repository, https://github.com/hymns/alertiqo-client-python
Keywords: alertiqo,error-tracking,python,sdk,monitoring
Classifier: Development Status :: 4 - Beta
Classifier: Intended Audience :: Developers
Classifier: License :: OSI Approved :: MIT License
Classifier: Programming Language :: Python :: 3
Classifier: Programming Language :: Python :: 3.8
Classifier: Programming Language :: Python :: 3.9
Classifier: Programming Language :: Python :: 3.10
Classifier: Programming Language :: Python :: 3.11
Classifier: Programming Language :: Python :: 3.12
Requires-Python: >=3.8
License-File: LICENSE
Requires-Dist: requests>=2.25.0
Dynamic: license-file
